{
  "destinationId": "cameron-highlands",
  "city": "Cameron Highlands",
  "country": "Malaysia",
  "transportAdvice": "The Cameron Highlands are best explored by car or booked tours; the main towns are walkable but attractions are spread along the mountain roads.",
  "safetyLevel": "safe",
  "waterSafety": "tap-safe",
  "costLevel": "budget",
  "timeZone": "UTC+8",
  "weather": [
    {
      "month": 1,
      "avgHighC": 24,
      "avgLowC": 12,
      "rainProbability": "low",
      "humidity": "moderate",
      "description": "Dry season with warm days and cool nights; pack layers."
    },
    {
      "month": 2,
      "avgHighC": 24,
      "avgLowC": 12,
      "rainProbability": "low",
      "humidity": "moderate",
      "description": "Continued dry weather; comfortable for outdoor exploration."
    },
    {
      "month": 3,
      "avgHighC": 24,
      "avgLowC": 13,
      "rainProbability": "moderate",
      "humidity": "moderate",
      "description": "Light rains begin; green landscapes emerge."
    },
    {
      "month": 4,
      "avgHighC": 23,
      "avgLowC": 13,
      "rainProbability": "high",
      "humidity": "high",
      "description": "Rainy season begins; afternoon downpours are common."
    },
    {
      "month": 5,
      "avgHighC": 22,
      "avgLowC": 12,
      "rainProbability": "high",
      "humidity": "high",
      "description": "Peak rain; mornings are usually clear for activities."
    },
    {
      "month": 6,
      "avgHighC": 21,
      "avgLowC": 11,
      "rainProbability": "moderate",
      "humidity": "moderate",
      "description": "Cooler and drier than peak rain months."
    },
    {
      "month": 7,
      "avgHighC": 20,
      "avgLowC": 10,
      "rainProbability": "moderate",
      "humidity": "moderate",
      "description": "Cool and relatively dry; great for hiking."
    },
    {
      "month": 8,
      "avgHighC": 21,
      "avgLowC": 10,
      "rainProbability": "moderate",
      "humidity": "moderate",
      "description": "Similar to July; pleasant daytime temperatures."
    },
    {
      "month": 9,
      "avgHighC": 22,
      "avgLowC": 11,
      "rainProbability": "moderate",
      "humidity": "moderate",
      "description": "Warming up with occasional showers."
    },
    {
      "month": 10,
      "avgHighC": 23,
      "avgLowC": 12,
      "rainProbability": "moderate",
      "humidity": "moderate",
      "description": "Second short rainy season in some areas."
    },
    {
      "month": 11,
      "avgHighC": 23,
      "avgLowC": 12,
      "rainProbability": "moderate",
      "humidity": "moderate",
      "description": "Drying out with warm, pleasant conditions."
    },
    {
      "month": 12,
      "avgHighC": 23,
      "avgLowC": 12,
      "rainProbability": "low",
      "humidity": "moderate",
      "description": "Dry season returns; ideal for travel."
    }
  ],
  "_meta": {
    "dataVersion": "2026-Q1",
    "lastVerified": "2026-02-28",
    "lastUpdated": "2026-02-28",
    "generatedBy": "script-v2",
    "reviewStatus": "auto-generated"
  }
}